torchbuilder/__init__.py
torchbuilder/_version.py
torchbuilder/cli.py
torchbuilder/utils.py
torchbuilder/init/__init__.py
torchbuilder/init/git.py
torchbuilder/init/project.py
torchbuilder/init/uv.py
torchbuilder/init/venv.py
torchbuilder/install/__init__.py
torchbuilder/install/copy_tree.py
torchbuilder/install/install.py
torchbuilder/install/remote.py
torchbuilder/install/remove.py
torchbuilder-1.0.3.dist-info/METADATA
torchbuilder-1.0.3.dist-info/WHEEL
torchbuilder-1.0.3.dist-info/entry_points.txt
torchbuilder-1.0.3.dist-info/RECORD
