Metadata-Version: 2.4
Name: torchbuilder
Version: 1.0.3
Summary: Easily build project templates
Project-URL: Homepage, https://github.com/anthol42/torchbuilder
Author-email: alavertu2@gmail.com
Requires-Python: >=3.13
Requires-Dist: typer>=0.16.0
